[{"title": "Codeforces Round (Div. 3)", "start": 1697976300000, "end": 1697983500000}, {"title": "Codeforces Round (Div. 2)", "start": 1697958300000, "end": 1697965500000}, {"title": "Codeforces Round (Div. 3)", "start": 1697121300000, "end": 1697128500000}, {"title": "Codeforces Round (Div. 1, based on COMPFEST 15 - Final Round)", "start": 1696755900000, "end": 1696763100000}, {"title": "Codeforces Round (Div. 2, based on COMPFEST 15 - Final Round)", "start": 1696755900000, "end": 1696763100000}, {"title": "Codeforces Round 901 (Div. 1)", "start": 1696084500000, "end": 1696091700000}, {"title": "Codeforces Round 901 (Div. 2)", "start": 1696084500000, "end": 1696091700000}]